{
  "slug": "2026-05-31-sapporo-lilac-tram",
  "title": "2026-05-31 Sapporo Lilac Tram Literary Prep",
  "summary": "traditional fashion illustrations: office, weekend, date, and active.",
  "summaryJa": "札幌のアルバム。色の軸はライラック。構成は仕事場、街歩き、飲食店、studio-sports。",
  "collection": "daily",
  "character": "",
  "notesHref": "logs/generation-2026-05.md",
  "sortOrder": 52,
  "images": [
    {
      "label": "01",
      "src": "assets/albums/daily/2026/05/2026-05-31-sapporo-lilac-tram/01-office-tram-stop-tailoring.webp",
      "width": 923,
      "height": 1704,
      "aspectRatio": "13:24",
      "alt": "Office tailoring fashion illustration at a lilac tram stop",
      "title": "01 Office tram-stop tailoring",
      "tags": "Fashion Illustration / Sapporo / office",
      "style": "fashion-illustration",
      "place": "sapporo",
      "category": "office",
      "occasion": "work",
      "venue": "workplace",
      "locationDetail": "tram-stop tailoring",
      "activity": "working",
      "outfit": "tailoring"
    },
    {
      "label": "02",
      "src": "assets/albums/daily/2026/05/2026-05-31-sapporo-lilac-tram/02-weekend-book-cafe-denim.webp",
      "width": 1023,
      "height": 1537,
      "aspectRatio": "2:3",
      "alt": "Weekend denim fashion illustration outside a book cafe",
      "title": "02 Weekend book-cafe denim",
      "tags": "Fashion Illustration / Sapporo / weekend",
      "style": "fashion-illustration",
      "place": "sapporo",
      "category": "weekend",
      "occasion": "everyday",
      "venue": "city-outdoor",
      "locationDetail": "book-cafe denim",
      "activity": "city-walk",
      "outfit": "casual-separates"
    },
    {
      "label": "03",
      "src": "assets/albums/daily/2026/05/2026-05-31-sapporo-lilac-tram/03-date-botanical-lilac-dress.webp",
      "width": 1023,
      "height": 1537,
      "aspectRatio": "2:3",
      "alt": "Date lilac dress fashion illustration in a botanical garden",
      "title": "03 Date botanical lilac dress",
      "tags": "Fashion Illustration / Sapporo / date",
      "style": "fashion-illustration",
      "place": "sapporo",
      "category": "date",
      "occasion": "social-date",
      "venue": "dining-bar",
      "locationDetail": "botanical garden",
      "activity": "dining-drinks",
      "outfit": "dress"
    },
    {
      "label": "04",
      "src": "assets/albums/daily/2026/05/2026-05-31-sapporo-lilac-tram/04-active-park-utility.webp",
      "width": 1024,
      "height": 1536,
      "aspectRatio": "2:3",
      "alt": "Active utility fashion illustration on a park path",
      "title": "04 Active park utility",
      "tags": "Fashion Illustration / Sapporo / active",
      "style": "fashion-illustration",
      "place": "sapporo",
      "category": "active",
      "occasion": "movement",
      "venue": "studio-sports",
      "locationDetail": "park utility",
      "activity": "sport-practice",
      "outfit": "activewear"
    }
  ]
}
