{
  "slug": "2026-06-18-hong-kong-orchid-chrome-rev2",
  "title": "2026-06-18 Hong Kong Orchid Chrome Rev2",
  "summary": "Rev2 Hong Kong set across Sham Shui Po fabric market, Tai Kwun heritage gallery, West Kowloon waterfront steps, and Central Star Ferry pier, using user feedback from the strong third candidate to emphasize personality, social energy, outfit choice, and composition.",
  "summaryJa": "香港のアルバム。色の軸はオーキッドクローム。構成はマーケット、ミュージアム、イベント会場、移動。",
  "collection": "daily",
  "character": "",
  "notesHref": "notes/albums/daily/2026/06/2026-06-18-hong-kong-orchid-chrome-rev2.md",
  "sortOrder": 20,
  "images": [
    {
      "label": "01",
      "src": "assets/albums/daily/2026/06/2026-06-18-hong-kong-orchid-chrome-rev2/01-market-sham-shui-po-beads-anime.webp",
      "width": 1024,
      "height": 1536,
      "aspectRatio": "2:3",
      "alt": "Adult 18-19 Hong Kong Sham Shui Po fabric market look with camp-collar shirt, bandeau inner, balloon shorts, slouch socks, Mary Jane sneakers, and orchid bead earrings",
      "title": "01 Market Sham Shui Po beads",
      "tags": "Anime Editorial / Hong Kong / market / 18-19-adult",
      "style": "anime-editorial",
      "place": "hong-kong",
      "category": "market",
      "occasion": "everyday",
      "venue": "market-retail",
      "locationDetail": "Sham Shui Po beads",
      "activity": "shopping",
      "outfit": "trousers-shorts"
    },
    {
      "label": "02",
      "src": "assets/albums/daily/2026/06/2026-06-18-hong-kong-orchid-chrome-rev2/02-gallery-tai-kwun-marker.webp",
      "width": 1024,
      "height": 1536,
      "aspectRatio": "2:3",
      "alt": "Adult late 20s Hong Kong Tai Kwun gallery look with sleeveless black linen waistcoat, charcoal wrap culottes, smoke-gray knee socks, silver pointed pumps, and sculptural clutch",
      "title": "02 Gallery Tai Kwun marker",
      "tags": "Marker Sketch / Hong Kong / gallery / 25-29",
      "style": "marker-sketch",
      "place": "hong-kong",
      "category": "gallery",
      "occasion": "creative-culture",
      "venue": "museum-gallery",
      "locationDetail": "Tai Kwun",
      "activity": "viewing-design",
      "outfit": "tailoring"
    },
    {
      "label": "03",
      "src": "assets/albums/daily/2026/06/2026-06-18-hong-kong-orchid-chrome-rev2/03-lounge-west-kowloon-steps-anime.webp",
      "width": 1023,
      "height": 1537,
      "aspectRatio": "2:3",
      "alt": "Adult early 20s Hong Kong West Kowloon waterfront music-event look with one-shoulder knit top, silver parachute half pants, sheer lilac knee socks, Mary Jane pumps, chrome shoulder bag, phone charm, and event ticket",
      "title": "03 Lounge West Kowloon steps",
      "tags": "Anime Editorial / Hong Kong / lounge / 20-24",
      "style": "anime-editorial",
      "place": "hong-kong",
      "category": "lounge",
      "occasion": "night-out",
      "venue": "event-venue",
      "locationDetail": "West Kowloon steps",
      "activity": "performance-going",
      "outfit": "trousers-shorts"
    },
    {
      "label": "04",
      "src": "assets/albums/daily/2026/06/2026-06-18-hong-kong-orchid-chrome-rev2/04-transit-star-ferry-digital.webp",
      "width": 1024,
      "height": 1536,
      "aspectRatio": "2:3",
      "alt": "Adult late 20s Hong Kong Central Star Ferry pier look with ivory draped blouse, graphite Bermuda shorts, sheer charcoal tights, ankle-strap low pumps, rain capelet, and chrome-gray crossbody",
      "title": "04 Transit Star Ferry digital",
      "tags": "Digital Painting / Hong Kong / transit / 25-29",
      "style": "digital-magazine-painting",
      "place": "hong-kong",
      "category": "transit",
      "occasion": "travel",
      "venue": "transit-hub",
      "locationDetail": "Star Ferry",
      "activity": "moving",
      "outfit": "tailoring"
    }
  ]
}
