{
  "slug": "2026-06-06-tokyo-daikanyama-rainy-lowrise-walk",
  "title": "2026-06-06 Tokyo Daikanyama Rainy Lowrise Walk",
  "summary": "concrete Daikanyama places: T-SITE, Log Road, Kyu Asakura House slope, and Sarugakucho listening lounge.",
  "summaryJa": "東京のアルバム。構成は街歩き、飲食店。",
  "collection": "daily",
  "character": "",
  "notesHref": "notes/albums/daily/2026/06/2026-06-06-tokyo-daikanyama-rainy-lowrise-walk.md",
  "sortOrder": 37,
  "images": [
    {
      "label": "01",
      "src": "assets/albums/daily/2026/06/2026-06-06-tokyo-daikanyama-rainy-lowrise-walk/01-weekend-tsite-bookshop-cel-anime.webp",
      "width": 1024,
      "height": 1536,
      "aspectRatio": "2:3",
      "alt": "Adult early 20s weekend look at a Daikanyama T-SITE style bookstore courtyard",
      "title": "01 Weekend T-SITE bookshop",
      "tags": "Cel Anime / Tokyo / weekend / using-object",
      "style": "anime-cel-polished",
      "place": "tokyo",
      "category": "weekend",
      "occasion": "everyday",
      "venue": "city-outdoor",
      "locationDetail": "T-SITE bookshop",
      "activity": "city-walk",
      "outfit": "casual-separates"
    },
    {
      "label": "02",
      "src": "assets/albums/daily/2026/06/2026-06-06-tokyo-daikanyama-rainy-lowrise-walk/02-outerwear-log-road-marker-sketch.webp",
      "width": 902,
      "height": 1744,
      "aspectRatio": "451:872",
      "alt": "Adult late 20s outerwear look walking through Log Road Daikanyama after rain",
      "title": "02 Outerwear Log Road",
      "tags": "Marker Sketch / Tokyo / outerwear / walking-stride",
      "style": "marker-sketch",
      "place": "tokyo",
      "category": "outerwear",
      "occasion": "weather-layer",
      "venue": "city-outdoor",
      "locationDetail": "Log Road",
      "activity": "weather-walk",
      "outfit": "outerwear-layer"
    },
    {
      "label": "03",
      "src": "assets/albums/daily/2026/06/2026-06-06-tokyo-daikanyama-rainy-lowrise-walk/03-date-kyu-asakura-slope-pbr-3d.webp",
      "width": 1024,
      "height": 1536,
      "aspectRatio": "2:3",
      "alt": "Adult late 20s date look on a wet stone slope near Kyu Asakura House",
      "title": "03 Date Kyu Asakura slope",
      "tags": "PBR 3D / Tokyo / date / over-shoulder",
      "style": "pbr-fashion-3d",
      "place": "tokyo",
      "category": "date",
      "occasion": "social-date",
      "venue": "dining-bar",
      "locationDetail": "Kyu Asakura slope",
      "activity": "dining-drinks",
      "outfit": "casual-separates"
    },
    {
      "label": "04",
      "src": "assets/albums/daily/2026/06/2026-06-06-tokyo-daikanyama-rainy-lowrise-walk/04-lounge-sarugakucho-record-soft-real.webp",
      "width": 1023,
      "height": 1537,
      "aspectRatio": "2:3",
      "alt": "Adult early 20s lounge look in a Sarugakucho listening lounge after rain",
      "title": "04 Lounge Sarugakucho record",
      "tags": "Soft Real Art / Tokyo / lounge / seated-side",
      "style": "soft-real-fashion-art",
      "place": "tokyo",
      "category": "lounge",
      "occasion": "night-out",
      "venue": "dining-bar",
      "locationDetail": "Sarugakucho record",
      "activity": "dining-drinks",
      "outfit": "casual-separates"
    }
  ]
}
